Workbook

Sheet Cover
A1: Cheesecoins Protocol — Arbitrum Grant Disbursement Schedule
A2: Working draft — May 7, 2026
A5: How to use this workbook:
A7: 1. Open the Disbursements sheet. Yellow cells are inputs you can change.
A8: 2. Adjust per-milestone bucket allocations until the totals work for you.
A9: 3. The Tranche Total column and grand totals at the bottom auto-recalculate.
A10: 4. The Repayment sheet shows the repayment-trigger logic — adjustable separately.
A11: 5. The Summary sheet auto-rolls bucket totals and percentages.
A13: When you're done, the final numbers get folded into the grant doc sections 6 and 7.
A15: Bucket meanings:
A16: - Promo: paid acquisition campaigns + partner incentive payments at thresholds
A17: - Liquidity: CURD/USDC seed on Uniswap V3 0.05% stablecoin tier
... A22: - CME: CME data licensing seed + first paid integration test

Sheet Milestones
A1: # | B1: Milestone | C1: Target date | D1: Trigger (on-chain verifiable)
A2: M1 | B2: 5 partners across 2+ tiers | C2: 46174 | D2: 5 setMerchantWithTier events on MerchantRegistry (likely already onboarded by M0 — fires immediately)
A3: M0 | B3: Grant accepted, promo campaign launches | C3: 46204 | D3: Grant agreement signed; promo spend begins (Greg starts onboarding partners independently in May 2026)
A4: M2 | B4: CME data agreement signed; integration test live on Sepolia | C4: 46204 | D4: Signed CME agreement + on-chain price update events on CommodityPriceOracle
A5: M3 | B5: 15 partners across 3+ tiers, CURD/USDC pool live | C5: 46235 | D5: 15 MerchantStatusChanged events + Uniswap V3 0.05% stablecoin pool deploy tx
A6: M4 | B6: First Commerce NFT project fully sold out | C6: 46235 | D6: All scenes in a partner Commerce NFT project hit SCENE_MAX_SUPPLY cap (REPAYMENT TRIGGER)
A7: M5 | B7: FxPeggedRedemption module audited and deployed to mainnet | C7: 46235 | D7: Audit report published + module configured on FiatRedemptionVault proxy
A8: M6 | B8: 30 partners across all 5 tiers | C8: 46357 | D8: 30 MerchantStatusChanged events covering all 5 Tier enum values
A9: M7 | B9: Nubians North NFT project 50% sellout | C9: 46447 | D9: mintedPerScene cumulative >= 50% of TOTAL_MAX_SUPPLY (25,000 of 50,000) — REPAYMENT TRIGGER

Sheet Disbursements
A1: Milestone | B1: Target date | C1: Promo | D1: Liquidity | E1: Founder dev | F1: Ops | G1: Contractor | H1: Audit | I1: CME | J1: Tranche total | K1: Cumulative
A2: M0 | B2: =VLOOKUP(A2, Milestones!A:C, 3, FALSE) | C2: 50000 | D2: 0 | E2: 3000 | F2: 2000 | G2: 0 | H2: 0 | I2: 0 | J2: =SUM(C2:I2) | K2: =J2
A3: M1 | B3: =VLOOKUP(A3, Milestones!A:C, 3, FALSE) | C3: 20000 | D3: 0 | E3: 3000 | F3: 2000 | G3: 0 | H3: 0 | I3: 0 | J3: =SUM(C3:I3) | K3: =K2+J3
A4: M2 | B4: =VLOOKUP(A4, Milestones!A:C, 3, FALSE) | C4: 0 | D4: 0 | E4: 3000 | F4: 2000 | G4: 0 | H4: 0 | I4: 8000 | J4: =SUM(C4:I4) | K4: =K3+J4
A5: M3 | B5: =VLOOKUP(A5, Milestones!A:C, 3, FALSE) | C5: 10000 | D5: 20000 | E5: 3000 | F5: 2000 | G5: 0 | H5: 0 | I5: 0 | J5: =SUM(C5:I5) | K5: =K4+J5
A6: M5 | B6: =VLOOKUP(A6, Milestones!A:C, 3, FALSE) | C6: 0 | D6: 0 | E6: 3000 | F6: 2000 | G6: 6000 | H6: 6000 | I6: 0 | J6: =SUM(C6:I6) | K6: =K5+J6
A7: M6 | B7: =VLOOKUP(A7, Milestones!A:C, 3, FALSE) | C7: 0 | D7: 0 | E7: 3000 | F7: 2000 | G7: 0 | H7: 0 | I7: 0 | J7: =SUM(C7:I7) | K7: =K6+J7
A8: Total | C8: =SUM(C2:C7) | D8: =SUM(D2:D7) | E8: =SUM(E2:E7) | F8: =SUM(F2:F7) | G8: =SUM(G2:G7) | H8: =SUM(H2:H7) | I8: =SUM(I2:I7) | J8: =SUM(J2:J7)
A10: Target | J10: 150000
A11: Variance | J11: =J8-J10

Sheet Summary
A1: Bucket | B1: Amount | C1: % of grant | D1: Release gate
A2: Promo | B2: =Disbursements!C8 | C2: =B2/Disbursements!J8 | D2: Tranched at M0 / M1 / M2 — front-loaded
A3: Liquidity | B3: =Disbursements!D8 | C3: =B3/Disbursements!J8 | D3: M2: CURD/USDC pool seed on Uniswap V3 0.05% stablecoin tier
A4: Founder dev | B4: =Disbursements!E8 | C4: =B4/Disbursements!J8 | D4: $3k per milestone × 6 milestones — milestone-tied not time-tied
A5: Ops | B5: =Disbursements!F8 | C5: =B5/Disbursements!J8 | D5: $2k per milestone × 6 milestones — multi-keeper infra, uptime, support
A6: Contractor | B6: =Disbursements!G8 | C6: =B6/Disbursements!J8 | D6: M3: external contractor capacity against FxPegged prep
A7: Audit | B7: =Disbursements!H8 | C7: =B7/Disbursements!J8 | D7: M6: contingency + final attestation; layers with Arbitrum Audit Program
A8: CME | B8: =Disbursements!I8 | C8: =B8/Disbursements!J8 | D8: M7: CME data licensing seed + first paid integration test
A9: Total | B9: =SUM(B2:B8) | C9: =SUM(C2:C8)

Sheet Repayment
A1: Cheesecoins -> Arbitrum DAO repayment schedule
A2: Repayment begins on the EARLIER of (a) or (b) below.
A4: Parameter | B4: Value | C4: Notes
A5: Grant amount | B5: 150000 | C5: Total ask, mirrors Disbursements grand total
A6: Repayment cap multiple | B6: 1.5 | C6: 1.5x = $225k cumulative repayment maximum
A7: Repayment cap (USD) | B7: =B5*B6 | C7: Auto-calc: grant amount * cap multiple
A8: Time cap (months) | B8: 36 | C8: From M2 (CME integration live)
A9: Subscription rev-share % | B9: 0.05 | C9: 5% of subscription revenue from Settlement Index consumers
A10: Commerce NFT fee % (existing) | B10: 0.05 | C10: Already deployed in ProjectSale
A11: Trigger (a): First Commerce NFT sold out | B11: M4 | C11: Smaller / earlier signal — partner project fully sold
A12: Trigger (b): Nubians North 50% sellout | B12: M7 | C12: Flagship collection at 25,000 of 50,000 minted
A13: Trigger (c): Subscription rev share | B13: M2 | C13: When Settlement Index integration goes live
A14: NFT-route repayment % of fees | B14: 1 | C14: % of protocol's 5% commerce fees that route to repayment escrow until cap is hit
A16: Mechanism
A17: Path A (NFT-route): when M4 (50% sellout of any Commerce NFT project) hits, the protocol's 5% commerce fee on subsequent NFT sales routes to a repayment escrow until the cap is hit. Off-chain accounting initially; can move to on-chain enforcement later.
A19: Path B (subscription-route): from M7 onward, 5% of Settlement Index subscription revenue from consumer protocols accrues to the Arbitrum DAO treasury until the cap is hit, or 36 months from M7 (whichever first).
A21: After cap is met, share drops to 0%. After cap is met OR 36 months from M7 (whichever first), obligation is fully satisfied.
